litecord/.DS_Store
litecord/__init__.py
litecord/py.typed
litecord-0.0.1.dev0.dist-info/METADATA
litecord-0.0.1.dev0.dist-info/WHEEL
litecord-0.0.1.dev0.dist-info/licenses/LICENSE
litecord-0.0.1.dev0.dist-info/RECORD
