Metadata-Version: 2.1
Name: litecord
Version: 0.0.1.dev0
Summary: An easy to use Discord Interactions API implementation.
Project-URL: Homepage, https://codeberg.org/monospacedmagic/litecord
Project-URL: Repository, https://codeberg.org/monospacedmagic/litecord
Author-email: monospacedmagic <luci@monospacedmagic.dev>
License: ISC
License-File: LICENSE
Keywords: api,discord,interactions,litecord,litestar,rest
Classifier: Development Status :: 2 - Pre-Alpha
Classifier: Environment :: Console
Classifier: Environment :: Web Environment
Classifier: Framework :: AnyIO
Classifier: Framework :: MkDocs
Classifier: Intended Audience :: Developers
Classifier: License :: OSI Approved :: ISC License (ISCL)
Classifier: Operating System :: OS Independent
Classifier: Programming Language :: Python
Classifier: Programming Language :: Python :: 3
Classifier: Programming Language :: Python :: 3 :: Only
Classifier: Programming Language :: Python :: 3.12
Classifier: Programming Language :: Python :: 3.13
Classifier: Topic :: Communications :: Chat
Classifier: Topic :: Documentation
Classifier: Topic :: Internet :: WWW/HTTP :: HTTP Servers
Classifier: Topic :: Software Development :: Libraries :: Python Modules
Classifier: Typing :: Typed
Requires-Python: >=3.12
Requires-Dist: litestar>=2.6.3
